ShiyongTensorflowGoujianJiqiXuexiXiangmuZhongwenbanChuyi/README.md
ShiyongTensorflowGoujianJiqiXuexiXiangmuZhongwenbanChuyi/__init__.py
ShiyongTensorflowGoujianJiqiXuexiXiangmuZhongwenbanChuyi/__main__.py
ShiyongTensorflowGoujianJiqiXuexiXiangmuZhongwenbanChuyi/file.epub
ShiyongTensorflowGoujianJiqiXuexiXiangmuZhongwenbanChuyi/index.html
ShiyongTensorflowGoujianJiqiXuexiXiangmuZhongwenbanChuyi/css/__init__.py
ShiyongTensorflowGoujianJiqiXuexiXiangmuZhongwenbanChuyi/css/annotations.css
ShiyongTensorflowGoujianJiqiXuexiXiangmuZhongwenbanChuyi/css/main.css
ShiyongTensorflowGoujianJiqiXuexiXiangmuZhongwenbanChuyi/css/normalize.css
ShiyongTensorflowGoujianJiqiXuexiXiangmuZhongwenbanChuyi/css/popup.css
ShiyongTensorflowGoujianJiqiXuexiXiangmuZhongwenbanChuyi/font/__init__.py
ShiyongTensorflowGoujianJiqiXuexiXiangmuZhongwenbanChuyi/font/fontello.eot
ShiyongTensorflowGoujianJiqiXuexiXiangmuZhongwenbanChuyi/font/fontello.svg
ShiyongTensorflowGoujianJiqiXuexiXiangmuZhongwenbanChuyi/font/fontello.ttf
ShiyongTensorflowGoujianJiqiXuexiXiangmuZhongwenbanChuyi/font/fontello.woff
ShiyongTensorflowGoujianJiqiXuexiXiangmuZhongwenbanChuyi/img/__init__.py
ShiyongTensorflowGoujianJiqiXuexiXiangmuZhongwenbanChuyi/img/annotator-glyph-sprite.png
ShiyongTensorflowGoujianJiqiXuexiXiangmuZhongwenbanChuyi/img/annotator-icon-sprite.png
ShiyongTensorflowGoujianJiqiXuexiXiangmuZhongwenbanChuyi/img/apple-touch-icon.png
ShiyongTensorflowGoujianJiqiXuexiXiangmuZhongwenbanChuyi/img/cancelfullscreen.png
ShiyongTensorflowGoujianJiqiXuexiXiangmuZhongwenbanChuyi/img/close.png
ShiyongTensorflowGoujianJiqiXuexiXiangmuZhongwenbanChuyi/img/fullscreen.png
ShiyongTensorflowGoujianJiqiXuexiXiangmuZhongwenbanChuyi/img/loader.gif
ShiyongTensorflowGoujianJiqiXuexiXiangmuZhongwenbanChuyi/img/menu-icon.png
ShiyongTensorflowGoujianJiqiXuexiXiangmuZhongwenbanChuyi/img/save.png
ShiyongTensorflowGoujianJiqiXuexiXiangmuZhongwenbanChuyi/img/saved.png
shiyong_tensorflow_goujian_jiqi_xuexi_xiangmu_zhongwenban_chuyi-2024.3.5.0.dist-info/METADATA
shiyong_tensorflow_goujian_jiqi_xuexi_xiangmu_zhongwenban_chuyi-2024.3.5.0.dist-info/WHEEL
shiyong_tensorflow_goujian_jiqi_xuexi_xiangmu_zhongwenban_chuyi-2024.3.5.0.dist-info/entry_points.txt
shiyong_tensorflow_goujian_jiqi_xuexi_xiangmu_zhongwenban_chuyi-2024.3.5.0.dist-info/top_level.txt
shiyong_tensorflow_goujian_jiqi_xuexi_xiangmu_zhongwenban_chuyi-2024.3.5.0.dist-info/RECORD
